xyz_tablestore/__init__.py
xyz_tablestore/config.py
xyz_tablestore/filterset.py
xyz_tablestore/lookup.py
xyz_tablestore/query.py
xyz_tablestore/rest_framework.py
xyz_tablestore/schema.py
xyz_tablestore/store.py
xyz_tablestore/utils.py
xyz_tablestore-0.0.17.dist-info/METADATA
xyz_tablestore-0.0.17.dist-info/WHEEL
xyz_tablestore-0.0.17.dist-info/top_level.txt
xyz_tablestore-0.0.17.dist-info/RECORD
